cheerlights_api/__init__.py
cheerlights_api/cheerlights_api.py
cheerlights_api-0.1.2.dist-info/LICENSE
cheerlights_api-0.1.2.dist-info/METADATA
cheerlights_api-0.1.2.dist-info/WHEEL
cheerlights_api-0.1.2.dist-info/top_level.txt
cheerlights_api-0.1.2.dist-info/RECORD
