Metadata-Version: 2.1
Name: cheerlights_api
Version: 0.1.2
Summary: A Python package to interact with the CheerLights API.
Home-page: https://github.com/cheerlights/cheerlights-python-package
Author: Hans Scharler
Author-email: hscharler@gmail.com
License: MIT
Classifier: Programming Language :: Python :: 3
Classifier: License :: OSI Approved :: MIT License
Classifier: Operating System :: OS Independent
Requires-Python: >=3.6
License-File: LICENSE
Requires-Dist: requests>=2.25.1
